src/bow/__about__.py
src/bow/__main__.py
templates/pycord/main.py
templates/pycordv3/main.py
bow_cli-1.0.0.7.dist-info/METADATA
bow_cli-1.0.0.7.dist-info/WHEEL
bow_cli-1.0.0.7.dist-info/entry_points.txt
bow_cli-1.0.0.7.dist-info/RECORD
